Mensajitos_saidnahum-6.0.data/scripts/test.py
paquete_mensajes/__init__.py
paquete_mensajes/subpaquete_adios/__init__.py
paquete_mensajes/subpaquete_adios/modulo_despedidas.py
paquete_mensajes/subpaquete_hola/__init__.py
paquete_mensajes/subpaquete_hola/modulo_saludos.py
Mensajitos_saidnahum-6.0.dist-info/LICENSE
Mensajitos_saidnahum-6.0.dist-info/METADATA
Mensajitos_saidnahum-6.0.dist-info/WHEEL
Mensajitos_saidnahum-6.0.dist-info/top_level.txt
Mensajitos_saidnahum-6.0.dist-info/RECORD
