Metadata-Version: 2.1
Name: Mensajitos-saidnahum
Version: 6.0
Summary: Un paquete para saludar y despedir
Home-page: https://sidn.ml
Author: Said Montes
Author-email: saidnahum.dev@gmail.com
Classifier: Environment :: Console
Classifier: Intended Audience :: Developers
Classifier: License :: OSI Approved :: MIT License
Classifier: Operating System :: OS Independent
Classifier: Programming Language :: Python
Classifier: Programming Language :: Python :: 3.9
Classifier: Programming Language :: Python :: 3.10
Classifier: Topic :: Utilities
License-File: LICENSE
Requires-Dist: numpy (==1.21.5)
